cmdfixer-0.1.1.dist-info/licenses/LICENSE
fix_cmd/__init__.py
fix_cmd/cli.py
fix_cmd/core.py
fix_cmd/rules.py
cmdfixer-0.1.1.dist-info/METADATA
cmdfixer-0.1.1.dist-info/WHEEL
cmdfixer-0.1.1.dist-info/top_level.txt
cmdfixer-0.1.1.dist-info/RECORD
