Metadata-Version: 2.4
Name: cmdfixer
Version: 0.1.1
Summary: Suggests corrections for mistyped CLI commands (git, Linux, etc.)
Author: Nikhil Kumar
Author-email: Nikhil Kumar <Kumarn7570@gmail.com>
License: MIT License
Project-URL: Homepage, https://github.com/yourusername/cmdfixer
Requires-Python: >=3.6
License-File: LICENSE
Requires-Dist: thefuzz>=0.20.0
Dynamic: author
Dynamic: license-file
Dynamic: requires-python
